pygaposa/__init__.py
pygaposa/__meta__.py
pygaposa/api.py
pygaposa/api_types.py
pygaposa/client.py
pygaposa/device.py
pygaposa/devicebase.py
pygaposa/firebase.py
pygaposa/gaposa.py
pygaposa/geoapi.py
pygaposa/group.py
pygaposa/model.py
pygaposa/motor.py
pygaposa/poll_manager.py
pygaposa/room.py
pygaposa/schedule.py
pygaposa-0.2.4.dist-info/LICENSE
pygaposa-0.2.4.dist-info/METADATA
pygaposa-0.2.4.dist-info/WHEEL
pygaposa-0.2.4.dist-info/top_level.txt
pygaposa-0.2.4.dist-info/RECORD
