Metadata-Version: 2.2
Name: pygaposa
Version: 0.2.4
Summary: Unofficial module for access to Gaposa morotized shades cloud API
Home-page: https://github.com/mwatson2/pygaposa
Author: Mark Watson
Author-email: markwatson@cantab.net
License: MIT
Classifier: Natural Language :: English
Classifier: Programming Language :: Python
Classifier: Programming Language :: Python :: 3
Classifier: Programming Language :: Python :: 3.9
Classifier: Programming Language :: Python :: 3.10
Classifier: Programming Language :: Python :: 3.11
Requires-Python: >=3.6
License-File: LICENSE
Requires-Dist: aiohttp
Requires-Dist: suncalc
Requires-Dist: typeguard
Provides-Extra: test
Requires-Dist: aioresponses; extra == "test"
Requires-Dist: asynctest; extra == "test"
Requires-Dist: parameterized; extra == "test"
Requires-Dist: pytest; extra == "test"
Requires-Dist: pytest-asyncio; extra == "test"
Requires-Dist: pytest-cov; extra == "test"
Requires-Dist: pytest-flake8; extra == "test"
Requires-Dist: pytest-mock; extra == "test"
Provides-Extra: docs
Requires-Dist: myst-parser; extra == "docs"
Requires-Dist: pypandoc>=1.6.3; extra == "docs"
Requires-Dist: readthedocs-sphinx-search; python_version >= "3.9" and extra == "docs"
Requires-Dist: sphinx<6,>=3.5.4; extra == "docs"
Requires-Dist: sphinx-autobuild; extra == "docs"
Requires-Dist: sphinx_book_theme; extra == "docs"
Requires-Dist: watchdog<1.0.0; python_version < "3.6" and extra == "docs"
Provides-Extra: dev
Requires-Dist: asynctest; extra == "dev"
Requires-Dist: black==23.1.0; extra == "dev"
Requires-Dist: identify>=1.4.20; extra == "dev"
Requires-Dist: parameterized; extra == "dev"
Requires-Dist: pre-commit; extra == "dev"
Requires-Dist: pytest-mock; extra == "dev"
Provides-Extra: all
Requires-Dist: aioresponses; extra == "all"
Requires-Dist: asynctest; extra == "all"
Requires-Dist: black==23.1.0; extra == "all"
Requires-Dist: identify>=1.4.20; extra == "all"
Requires-Dist: myst-parser; extra == "all"
Requires-Dist: parameterized; extra == "all"
Requires-Dist: pre-commit; extra == "all"
Requires-Dist: pypandoc>=1.6.3; extra == "all"
Requires-Dist: pytest; extra == "all"
Requires-Dist: pytest-asyncio; extra == "all"
Requires-Dist: pytest-cov; extra == "all"
Requires-Dist: pytest-flake8; extra == "all"
Requires-Dist: pytest-mock; extra == "all"
Requires-Dist: readthedocs-sphinx-search; python_version >= "3.9" and extra == "all"
Requires-Dist: sphinx-autobuild; extra == "all"
Requires-Dist: sphinx<6,>=3.5.4; extra == "all"
Requires-Dist: sphinx_book_theme; extra == "all"
Requires-Dist: watchdog<1.0.0; python_version < "3.6" and extra == "all"
Dynamic: author
Dynamic: author-email
Dynamic: classifier
Dynamic: description
Dynamic: description-content-type
Dynamic: home-page
Dynamic: license
Dynamic: provides-extra
Dynamic: requires-dist
Dynamic: requires-python
Dynamic: summary
